ggi-0.6.0.data/data/bin/catpv
ggi-0.6.0.data/data/bin/consel
ggi-0.6.0.data/data/bin/makermt
ggi-0.6.0.data/data/bin/raxmlHPC-SSE3_Darwin_64bit
ggi-0.6.0.data/data/bin/seqmt
ggi-0.6.0.data/scripts/root_groups.py
ggpy/__init__.py
ggpy/classifier.py
ggpy/cli.py
ggpy/filter_hypos.py
ggpy/ggi.py
ggpy/utils.py
ggpy/wrappers.py
ggpy/data/g_3_rooted.tree
ggpy/data/g_3_unrooted.tree
ggpy/data/g_4_rooted.tree
ggpy/data/g_4_unrooted.tree
ggpy/data/g_5_rooted.tree
ggpy/data/g_5_unrooted.tree
ggpy/data/g_6_rooted.tree
ggpy/data/g_6_unrooted.tree
ggpy/data/g_7_rooted.tree
ggpy/data/g_7_unrooted.tree
ggpy/data/g_8_rooted.tree
ggpy/data/g_8_unrooted.tree
ggpy/data/g_9_unrooted.tree
ggi-0.6.0.dist-info/LICENSE
ggi-0.6.0.dist-info/METADATA
ggi-0.6.0.dist-info/WHEEL
ggi-0.6.0.dist-info/entry_points.txt
ggi-0.6.0.dist-info/top_level.txt
ggi-0.6.0.dist-info/RECORD
