Metadata-Version: 2.1
Name: ggi
Version: 0.6.0
Summary: UNKNOWN
Home-page: https://github.com/Ulises-Rosas/GGpy
Maintainer: Ulises Rosas
License: UNKNOWN
Platform: UNKNOWN
Classifier: Programming Language :: Python :: 3
License-File: LICENSE
Requires-Dist: dendropy (==4.4.0)
